serverless_fastapi/__init__.py
serverless_fastapi/config.py
serverless_fastapi/db.py
serverless_fastapi/main.py
serverless_fastapi/mangum/__init__.py
serverless_fastapi/mangum/adapter.py
serverless_fastapi/mangum/exceptions.py
serverless_fastapi/mangum/types.py
serverless_fastapi/mangum/handlers/__init__.py
serverless_fastapi/mangum/handlers/alb.py
serverless_fastapi/mangum/handlers/api_gateway.py
serverless_fastapi/mangum/handlers/lambda_at_edge.py
serverless_fastapi/mangum/handlers/utils.py
serverless_fastapi/mangum/protocols/__init__.py
serverless_fastapi/mangum/protocols/http.py
serverless_fastapi/mangum/protocols/lifespan.py
serverless_fastapi-0.1.0.dist-info/LICENSE
serverless_fastapi-0.1.0.dist-info/METADATA
serverless_fastapi-0.1.0.dist-info/WHEEL
serverless_fastapi-0.1.0.dist-info/top_level.txt
serverless_fastapi-0.1.0.dist-info/RECORD
