Metadata-Version: 2.1
Name: serverless-fastapi
Version: 0.1.0
Summary: Serverless FastAPI
Author-email: Oscar Bahamonde <oscar.bahamonde@hatarini.com>
License: Copyright 2022 Oscar Bahamonde
Project-URL: Homepage, https://github.com/oscarbahamonde/serverless-fastapi
Project-URL: Bug Tracker, https://github.com/oscarbahamonde/serverless-fastapi/issues
Keywords: serverless,fastapi,aws,lambda
Classifier: License :: OSI Approved :: MIT License
Classifier: Programming Language :: Python
Classifier: Programming Language :: Python :: 3
Requires-Python: >=3.8
License-File: LICENSE
Provides-Extra: dev
Requires-Dist: black ; extra == 'dev'
Requires-Dist: pytest ; extra == 'dev'
